AUTHORS
CHANGES
LICENSE
MANIFEST.in
setup.cfg
setup.py
docs/TODO.rst
pithos/__init__.py
pithos/authsession.py
pithos/filesystem.py
pithos/flask.py
pithos/handler.py
pithos/redis.py
pithos/session.py
pithos/store.py
pithos.egg-info/PKG-INFO
pithos.egg-info/SOURCES.txt
pithos.egg-info/dependency_links.txt
pithos.egg-info/not-zip-safe
pithos.egg-info/requires.txt
pithos.egg-info/top_level.txt
tests/__init__.py
tests/conftest.py
tests/test_filesystem.py
tests/test_handler.py
tests/test_redis.py