Metadata-Version: 1.1
Name: pithos
Version: 0.0.3
Summary: Session handling for web applications
Home-page: https://github.com/Dreamsolution/pithos
Author: Rudolph Froger
Author-email: rudolphfroger@dreamsolution.nl
License: MIT
Platform: any
Classifier: Development Status :: 3 - Alpha
Classifier: Intended Audience :: Developers
Classifier: License :: OSI Approved :: MIT License
Classifier: Topic :: Internet :: WWW/HTTP
Classifier: Programming Language :: Python :: 3.4
Classifier: Programming Language :: Python :: 3.5
Classifier: Programming Language :: Python :: Implementation :: CPython
Classifier: Topic :: Software Development :: Libraries :: Python Modules
